tkintertools/three/__init__.py
tkintertools/three/engine.py
tkintertools/three/geometries.py
tkintertools_3d-1.0.3.dist-info/LICENSE.txt
tkintertools_3d-1.0.3.dist-info/METADATA
tkintertools_3d-1.0.3.dist-info/WHEEL
tkintertools_3d-1.0.3.dist-info/top_level.txt
tkintertools_3d-1.0.3.dist-info/RECORD
