Metadata-Version: 2.2
Name: tkintertools-3d
Version: 1.0.3
Summary: Extension package for tkintertools to simple 3D drawings
Author-email: Xiaokang2022 <2951256653@qq.com>
Maintainer-email: Xiaokang2022 <2951256653@qq.com>
License: MIT License
Project-URL: Bug tracker, https://github.com/Xiaokang2022/tkintertools-3d/issues
Project-URL: Source code, https://github.com/Xiaokang2022/tkintertools-3d
Keywords: tkinter,tkintertools,3d,cross-platform
Classifier: Programming Language :: Python :: 3
Classifier: License :: OSI Approved :: MIT License
Classifier: Operating System :: Microsoft :: Windows
Classifier: Operating System :: POSIX :: Linux
Classifier: Operating System :: MacOS
Classifier: Intended Audience :: Developers
Classifier: Typing :: Typed
Requires-Python: >=3.10
License-File: LICENSE.txt
Requires-Dist: tkintertools>=3.0.0rc6
Requires-Dist: typing-extensions
